pytest_insper/__init__.py
pytest_insper/fixtures.py
pytest_insper/util.py
pytest_insper-0.1.4.dist-info/LICENSE
pytest_insper-0.1.4.dist-info/METADATA
pytest_insper-0.1.4.dist-info/WHEEL
pytest_insper-0.1.4.dist-info/entry_points.txt
pytest_insper-0.1.4.dist-info/top_level.txt
pytest_insper-0.1.4.dist-info/RECORD
